latticeadaptor/__init__.py
latticeadaptor/core.py
latticeadaptor/lark/Madx.lark
latticeadaptor/lark/__init__.py
latticeadaptor/mappings/__init__.py
latticeadaptor/mappings/elegant_attribute_map.json
latticeadaptor/mappings/elegant_columns.json
latticeadaptor/mappings/elegant_element_map.json
latticeadaptor/mappings/madx_columns.json
latticeadaptor/mappings/tracy_attribute_map.json
latticeadaptor/mappings/tracy_columns.json
latticeadaptor/mappings/tracy_element_map.json
latticeadaptor/parsers/__init__.py
latticeadaptor/utils/__init__.py
latticeadaptor-0.3.23.dist-info/entry_points.txt
latticeadaptor-0.3.23.dist-info/LICENSE
latticeadaptor-0.3.23.dist-info/WHEEL
latticeadaptor-0.3.23.dist-info/METADATA
latticeadaptor-0.3.23.dist-info/RECORD
