Metadata-Version: 2.1
Name: latticeadaptor
Version: 0.3.23
Summary: <Enter a one-sentence description of this project here.>
Home-page: https://github.com/tomerten/latticeadaptor
License: MIT
Keywords: packaging,poetry
Author: Tom Mertens
Author-email: your.email@whatev.er
Requires-Python: >=3.8,<4.0
Classifier: License :: OSI Approved :: MIT License
Classifier: Programming Language :: Python :: 3
Classifier: Programming Language :: Python :: 3.8
Classifier: Programming Language :: Python :: 3.9
Requires-Dist: LatticeJSON (>=0.1.6,<0.2.0)
Requires-Dist: cpymad (>=1.8.1,<2.0.0)
Requires-Dist: ipykernel (>=5.5.5,<6.0.0)
Requires-Dist: ipython (>=7.23.1,<8.0.0)
Requires-Dist: lark (>=0.11.3,<0.12.0)
Requires-Dist: latticeconstructor (>=0.2.3,<0.3.0)
Requires-Dist: matplotlib (>=3.4.1,<4.0.0)
Requires-Dist: nbsphinx (>=0.8.5,<0.9.0)
Requires-Dist: pandas (>=1.2.4,<2.0.0)
Requires-Dist: pandoc (>=1.0.2,<2.0.0)
Requires-Dist: termcolor (>=1.1.0,<2.0.0)
Project-URL: Repository, https://github.com/tomerten/latticeadaptor
